xviewer/__init__.py
xviewer/_version.py
xviewer/handlers.py
xviewer/tests/__init__.py
xviewer/tests/test_handlers.py
xviewer-0.0.2.data/data/etc/jupyter/jupyter_notebook_config.d/xviewer.json
xviewer-0.0.2.data/data/etc/jupyter/jupyter_server_config.d/xviewer.json
xviewer-0.0.2.data/data/share/jupyter/labextensions/@datalayer/xviewer/build_log.json
xviewer-0.0.2.data/data/share/jupyter/labextensions/@datalayer/xviewer/package.json
xviewer-0.0.2.data/data/share/jupyter/labextensions/@datalayer/xviewer/schemas/@datalayer/jupyter-aws/package.json.orig
xviewer-0.0.2.data/data/share/jupyter/labextensions/@datalayer/xviewer/schemas/@datalayer/jupyter-aws/plugin.json
xviewer-0.0.2.data/data/share/jupyter/labextensions/@datalayer/xviewer/static/design_icons_lib_index_js.cae868cc022ddf18d113.js
xviewer-0.0.2.data/data/share/jupyter/labextensions/@datalayer/xviewer/static/design_icons_lib_index_js.cae868cc022ddf18d113.js.map
xviewer-0.0.2.data/data/share/jupyter/labextensions/@datalayer/xviewer/static/lib_index_js.8f95b61b59acc237d450.js
xviewer-0.0.2.data/data/share/jupyter/labextensions/@datalayer/xviewer/static/lib_index_js.8f95b61b59acc237d450.js.map
xviewer-0.0.2.data/data/share/jupyter/labextensions/@datalayer/xviewer/static/remoteEntry.b6092ee64cdf986eeb17.js
xviewer-0.0.2.data/data/share/jupyter/labextensions/@datalayer/xviewer/static/remoteEntry.b6092ee64cdf986eeb17.js.map
xviewer-0.0.2.data/data/share/jupyter/labextensions/@datalayer/xviewer/static/style.js
xviewer-0.0.2.data/data/share/jupyter/labextensions/@datalayer/xviewer/static/style_index_js.859b9929c33397270eb1.js
xviewer-0.0.2.data/data/share/jupyter/labextensions/@datalayer/xviewer/static/style_index_js.859b9929c33397270eb1.js.map
xviewer-0.0.2.data/data/share/jupyter/labextensions/@datalayer/xviewer/static/vendors-node_modules_css-loader_dist_runtime_api_js-node_modules_css-loader_dist_runtime_cssW-72eba1.058d212bf4401555a141.js
xviewer-0.0.2.dist-info/METADATA
xviewer-0.0.2.dist-info/WHEEL
xviewer-0.0.2.dist-info/licenses/LICENSE
xviewer-0.0.2.dist-info/RECORD
